cloud_vision/__init__.py
cloud_vision/configs.py
cloud_vision/httpclient.py
cloud_vision/models.py
cloud_vision/utils.py
cloud_vision/visionclient.py
cloud_vision/visionconfig.py
cloud_vision/example/example.py
cloud_vision/example/external_example.py
cloud_vision/example/nlp_translate_example.py
cloud_vision/example/ocr_example.py
cloud_vision/example/ocr_translate_example.py
cloud_vision/example/translate_example.py
cloud_vision/example/vision_example.py
cloud_vision_sdk-0.5.0.dist-info/DESCRIPTION.rst
cloud_vision_sdk-0.5.0.dist-info/METADATA
cloud_vision_sdk-0.5.0.dist-info/RECORD
cloud_vision_sdk-0.5.0.dist-info/WHEEL
cloud_vision_sdk-0.5.0.dist-info/metadata.json
cloud_vision_sdk-0.5.0.dist-info/top_level.txt
