Metadata-Version: 2.0
Name: cloud-vision-sdk
Version: 0.5.0
Summary: Xiaomi Cloud-Vision SDK
Home-page: UNKNOWN
Author: Xiaomi
Author-email: UNKNOWN
License: UNKNOWN
Platform: UNKNOWN
Requires-Dist: requests (>=2.6.0)
